tgext.admin_jmr-0.7.4-py3.11-nspkg.pth
tgext/admin/__init__.py
tgext/admin/config.py
tgext/admin/controller.py
tgext/admin/layouts.py
tgext/admin/mongo.py
tgext/admin/tgadminconfig.py
tgext/admin/utils.py
tgext/admin/widgets.py
tgext/admin/templates/__init__.py
tgext/admin/templates/bootstrap_form_layout.html
tgext/admin/templates/bootstrap_form_layout.jinja
tgext/admin/templates/bootstrap_form_layout.kajiki
tgext/admin/templates/bootstrap_form_layout.mak
tgext/admin/templates/bootstrap_grouped_index.html
tgext/admin/templates/bootstrap_grouped_index.xhtml
tgext/admin/templates/bootstrap_index.html
tgext/admin/templates/bootstrap_index.jinja
tgext/admin/templates/bootstrap_index.mak
tgext/admin/templates/bootstrap_index.xhtml
tgext/admin/templates/index.html
tgext/admin/templates/index.jinja
tgext/admin/templates/index.mak
tgext/admin/templates/index.xhtml
tgext/admin/templates/bootstrap_crud/__init__.py
tgext/admin/templates/bootstrap_crud/edit.html
tgext/admin/templates/bootstrap_crud/edit.jinja
tgext/admin/templates/bootstrap_crud/edit.mak
tgext/admin/templates/bootstrap_crud/edit.xhtml
tgext/admin/templates/bootstrap_crud/get_all.html
tgext/admin/templates/bootstrap_crud/get_all.jinja
tgext/admin/templates/bootstrap_crud/get_all.mak
tgext/admin/templates/bootstrap_crud/get_all.xhtml
tgext/admin/templates/bootstrap_crud/new.html
tgext/admin/templates/bootstrap_crud/new.jinja
tgext/admin/templates/bootstrap_crud/new.mak
tgext/admin/templates/bootstrap_crud/new.xhtml
tgext.admin_jmr-0.7.4.dist-info/METADATA
tgext.admin_jmr-0.7.4.dist-info/WHEEL
tgext.admin_jmr-0.7.4.dist-info/namespace_packages.txt
tgext.admin_jmr-0.7.4.dist-info/top_level.txt
tgext.admin_jmr-0.7.4.dist-info/RECORD
